slimjim/__init__.py
slimjim/codebox.py
slimjim/file_frame.py
slimjim/matics_box.py
slimjim/spec_frame.py
slimjim/util.py
slimjim-0.0.4.data/scripts/slimfile
slimjim-0.0.4.data/scripts/slimspec
slimjim-0.0.4.dist-info/LICENSE
slimjim-0.0.4.dist-info/METADATA
slimjim-0.0.4.dist-info/WHEEL
slimjim-0.0.4.dist-info/top_level.txt
slimjim-0.0.4.dist-info/RECORD
