Metadata-Version: 2.1
Name: slimjim
Version: 0.0.4
Summary: Hackish keystroke injection tool 
Home-page: https://github.com/cltrudeau/slimjim
Author: Christopher Trudeau
Author-email: ctrudeau+pypi@arsensa.com
License: MIT
Platform: UNKNOWN
Classifier: Development Status :: 3 - Alpha
Classifier: Intended Audience :: Developers
Classifier: License :: OSI Approved :: MIT License
Classifier: Operating System :: MacOS
Classifier: Programming Language :: Python :: 3.10
License-File: LICENSE
Requires-Dist: asciimatics (>=1.13.0)
